wgnsite-0.0.5.data/scripts/wgnsite
wgnsite_lib/__init__.py
wgnsite-0.0.5.dist-info/LICENSE
wgnsite-0.0.5.dist-info/METADATA
wgnsite-0.0.5.dist-info/WHEEL
wgnsite-0.0.5.dist-info/top_level.txt
wgnsite-0.0.5.dist-info/RECORD
